[{
  "topic": "Autot",
  "subtopics": [{
    "topic": "Virittely ja korjaaminen"
  }, {
    "topic": "Autolla ajaminen"
  }, {
    "topic": "Urheiluautot"
  }, {
    "topic": "Raskaat ajoneuvot"
  }, {
    "topic": "Henkilöautot"
  }]
}, {
  "topic": "Musiikki",
  "subtopics": []
}, {
  "topic": "Luonto ja ympäristö",
  "subtopics": []
}, {
  "topic": "Käsin tekeminen",
  "subtopics": []
}, {
  "topic": "Taide",
  "subtopics": []
}, {
  "topic": "Terveys",
  "subtopics": []
}, {
  "topic": "Ruoka",
  "subtopics": []
}, {
  "topic": "Matkailu",
  "subtopics": []
}, {
  "topic": "Lapset ja nuoret",
  "subtopics": []
}, {
  "topic": "Rakentaminen",
  "subtopics": []
}, {
  "topic": "Talous- ja raha-asiat",
  "subtopics": []
}, {
  "topic": "Koneet",
  "subtopics": []
}, {
  "topic": "Lukeminen",
  "subtopics": []
}, {
  "topic": "Kielet",
  "subtopics": []
}, {
  "topic": "Tietokoneet",
  "subtopics": []
}, {
  "topic": "Ihmisten auttaminen",
  "subtopics": []
}]