{
  "$schema": "http://json-schema.org/draft-07/schema#",

  "definitions": {
    "DocumentId": {
      "type": "string"
    }
  },

  "title": "RecommendationModel",
  "type": "object",
  "properties": {
    "applicationEnd": { "type": "number" },
    "applicationName": { "type": "string" },
    "applicationOnGoing": { "type": "boolean" },
    "applicationStart": { "type": "number" },
    "id": { "$ref": "#/definitions/DocumentId" },
    "name": { "type": "string" },
    "offerId": { "type": "string" },
    "degreeTitle": { "type": "string" },
    "educationCode": { "type": "string" },
    "educationDegreeName": { "type": "string" },
    "educationDomain": { "type": "string" },
    "goals": { "type": "string" },
    "providerName": { "type": "string" },
    "providerProvince": { "type": "string" },
    "similarity": { "type": "number" },
    "koulutuskoodi": { "type": "string" },
    "creditValue": { "type": "string" },
    "creditUnitShort": { "type": "string" },
    "type": { "type": "string" }
  },
  "required": [
    "applicationName",
    "applicationOnGoing",
    "applicationStart",
    "id",
    "name",
    "degreeTitle",
    "educationCode",
    "educationDegreeName",
    "educationDomain",
    "goals",
    "providerName",
    "providerProvince",
    "similarity",
    "type"
  ],
  "additionalProperties": false
}